lambdagram/__init__.py
lambdagram/bot.py
lambdagram-0.9.4.dist-info/DESCRIPTION.rst
lambdagram-0.9.4.dist-info/METADATA
lambdagram-0.9.4.dist-info/RECORD
lambdagram-0.9.4.dist-info/WHEEL
lambdagram-0.9.4.dist-info/metadata.json
lambdagram-0.9.4.dist-info/top_level.txt
