Metadata-Version: 2.0
Name: lambdagram
Version: 0.9.4
Summary: telegram bot wrapper with webhook for aws lambda
Home-page: https://github.com/jwkcp/lambdagram
Author: Jaewoong
Author-email: jaewoong.go@gmail.com
License: UNKNOWN
Download-URL: https://pypi.org/project/lambdagram/#files
Keywords: telegram,aws,lambda
Platform: UNKNOWN
Classifier: Programming Language :: Python :: 3
Classifier: Programming Language :: Python :: 3.2
Classifier: Programming Language :: Python :: 3.3
Classifier: Programming Language :: Python :: 3.4
Classifier: Programming Language :: Python :: 3.5
Classifier: Programming Language :: Python :: 3.6
Requires-Python: >=3
Requires-Dist: requests
